mopidy_musicbox_webclient/__init__.py
mopidy_musicbox_webclient/ext.conf
mopidy_musicbox_webclient/web.py
mopidy_musicbox_webclient/webclient.py
mopidy_musicbox_webclient/static/dialog-success.html
mopidy_musicbox_webclient/static/index.html
mopidy_musicbox_webclient/static/mb.appcache
mopidy_musicbox_webclient/static/system.html
mopidy_musicbox_webclient/static/css/webclient.css
mopidy_musicbox_webclient/static/images/default_cover.png
mopidy_musicbox_webclient/static/images/empty.png
mopidy_musicbox_webclient/static/images/loader.gif
mopidy_musicbox_webclient/static/images/user_24x32.png
mopidy_musicbox_webclient/static/images/icons/musicbox114.png
mopidy_musicbox_webclient/static/images/icons/musicbox32.gif
mopidy_musicbox_webclient/static/images/icons/musicbox32.png
mopidy_musicbox_webclient/static/images/icons/musicbox57.png
mopidy_musicbox_webclient/static/images/icons/musicbox72.png
mopidy_musicbox_webclient/static/images/icons/play_alt_12x12.png
mopidy_musicbox_webclient/static/images/icons/play_alt_16x16.png
mopidy_musicbox_webclient/static/js/controls.js
mopidy_musicbox_webclient/static/js/custom_scripting.js
mopidy_musicbox_webclient/static/js/functionsvars.js
mopidy_musicbox_webclient/static/js/gui.js
mopidy_musicbox_webclient/static/js/images.js
mopidy_musicbox_webclient/static/js/library.js
mopidy_musicbox_webclient/static/js/process_ws.js
mopidy_musicbox_webclient/static/js/synced_timer.js
mopidy_musicbox_webclient/static/vendors/font_awesome/css/font-awesome.css
mopidy_musicbox_webclient/static/vendors/font_awesome/css/font-awesome.min.css
mopidy_musicbox_webclient/static/vendors/font_awesome/fonts/FontAwesome.otf
mopidy_musicbox_webclient/static/vendors/font_awesome/fonts/fontawesome-webfont.eot
mopidy_musicbox_webclient/static/vendors/font_awesome/fonts/fontawesome-webfont.svg
mopidy_musicbox_webclient/static/vendors/font_awesome/fonts/fontawesome-webfont.ttf
mopidy_musicbox_webclient/static/vendors/font_awesome/fonts/fontawesome-webfont.woff
Mopidy_MusicBox_Webclient-3.1.0.dist-info/LICENSE
Mopidy_MusicBox_Webclient-3.1.0.dist-info/METADATA
Mopidy_MusicBox_Webclient-3.1.0.dist-info/WHEEL
Mopidy_MusicBox_Webclient-3.1.0.dist-info/entry_points.txt
Mopidy_MusicBox_Webclient-3.1.0.dist-info/top_level.txt
Mopidy_MusicBox_Webclient-3.1.0.dist-info/RECORD
